cms/__init__.py
cms/combine_corrlib.py
cms/common.py
cms/plotting.py
cms/reader_EcalElf.py
cms/reader_higgsDNA.py
cms/time_equalisation.py
cms/validation_dyll.py
cms_sas_utils-0.3.dist-info/METADATA
cms_sas_utils-0.3.dist-info/WHEEL
cms_sas_utils-0.3.dist-info/entry_points.txt
cms_sas_utils-0.3.dist-info/top_level.txt
cms_sas_utils-0.3.dist-info/RECORD
